DOOM/__init__.py
DOOM/__main__.py
DOOM/config.py
DOOM/doom.py
DOOM/utils/__init__.py
DOOM/utils/prompt_util.py
DOOM/utils/url_util.py
DOOM/utils/util.py
doomgit-0.1.0.dist-info/LICENSE
doomgit-0.1.0.dist-info/METADATA
doomgit-0.1.0.dist-info/WHEEL
doomgit-0.1.0.dist-info/entry_points.txt
doomgit-0.1.0.dist-info/top_level.txt
doomgit-0.1.0.dist-info/RECORD
